rompt/__init__.py
rompt/__main__.py
rompt/bindings.py
rompt/common.py
rompt/generate.py
rompt/main.py
rompt/pull.py
rompt/track.py
rompt-1.0.1.dist-info/LICENSE
rompt-1.0.1.dist-info/METADATA
rompt-1.0.1.dist-info/WHEEL
rompt-1.0.1.dist-info/entry_points.txt
rompt-1.0.1.dist-info/top_level.txt
rompt-1.0.1.dist-info/RECORD
