Metadata-Version: 2.1
Name: rompt
Version: 1.0.1
Summary: Python library to interact with the Rompt API and CLI.
Home-page: https://github.com/rompt-ai/rompt-py
Author: Rompt.ai
Author-email: admin@rompt.ai
License: MIT
Requires-Python: >=3.8
License-File: LICENSE
Requires-Dist: requests (>=2.27.1)
